data2neo/__init__.py
data2neo/utils.py
data2neo/common_modules/__init__.py
data2neo/common_modules/datetime.py
data2neo/common_modules/types.py
data2neo/core/__init__.py
data2neo/core/converter.py
data2neo/core/global_state.py
data2neo/core/parsetab.py
data2neo/core/resource_iterator.py
data2neo/core/schema_compiler.py
data2neo/core/factories/__init__.py
data2neo/core/factories/factory.py
data2neo/core/factories/factory_wrappers.py
data2neo/core/factories/matcher.py
data2neo/core/factories/registrar.py
data2neo/core/factories/resource.py
data2neo/neo4j/__init__.py
data2neo/neo4j/cypher.py
data2neo/neo4j/encoder.py
data2neo/neo4j/graph_elements.py
data2neo/relational_modules/__init__.py
data2neo/relational_modules/pandas.py
data2neo/relational_modules/sqlite.py
data2neo-1.4.3.dist-info/LICENSE
data2neo-1.4.3.dist-info/METADATA
data2neo-1.4.3.dist-info/WHEEL
data2neo-1.4.3.dist-info/top_level.txt
data2neo-1.4.3.dist-info/RECORD
