Metadata-Version: 2.1
Name: data2neo
Version: 1.4.3
Summary: Library for converting relational data into graph data (neo4j)
Home-page: https://github.com/jkminder/data2neo
Author: Julian Minder
Author-email: jminder@ethz.ch
Requires-Python: >=3.8
License-File: LICENSE
Requires-Dist: pandas >=1.5.2
Requires-Dist: ply >=3.11
Requires-Dist: neo4j >=5.11.0
